akarsu/__init__.py
akarsu/__main__.py
akarsu/akarsu.py
akarsu-0.2.0.dist-info/LICENSE.txt
akarsu-0.2.0.dist-info/METADATA
akarsu-0.2.0.dist-info/WHEEL
akarsu-0.2.0.dist-info/entry_points.txt
akarsu-0.2.0.dist-info/top_level.txt
akarsu-0.2.0.dist-info/RECORD
