Metadata-Version: 2.1
Name: akarsu
Version: 0.2.0
Summary: New Generation Profiler based on PEP 669
Author-email: Furkan Onder <furkanonder@protonmail.com>
License: The MIT License (MIT)
Project-URL: Homepage, https://github.com/furkanonder/akarsu
Project-URL: Bug Reports, https://github.com/furkanonder/akarsu/issues
Project-URL: Source, https://github.com/furkanonder/akarsu
Keywords: profiler,PEP669
Classifier: Development Status :: 3 - Alpha
Classifier: Environment :: Console
Classifier: Intended Audience :: Developers
Classifier: License :: OSI Approved :: MIT License
Classifier: Operating System :: OS Independent
Classifier: Programming Language :: Python
Classifier: Programming Language :: Python :: 3 :: Only
Classifier: Programming Language :: Python :: 3.12
Classifier: Topic :: Software Development :: Libraries :: Python Modules
Requires-Python: >=3.12
License-File: LICENSE.txt
